{
  "id": {
    "valgaar": "2021",
    "valgtype": "ST",
    "nivaa": "stemmekrets",
    "navn": "Uoppgitt krets",
    "nr": "0000"
  },
  "tidspunkt": {
    "rapportGenerert": "2021-09-14T21:20:27",
    "sisteStemmer": "2021-09-14T21:20:18"
  },
  "merknader": [],
  "antallsb": 636,
  "mandater": {
    "antall": 0,
    "endring": null
  },
  "stemmer": {
    "total": 23906,
    "fhs": 23875,
    "totalForkastede": 43,
    "fhsForkastede": 43
  },
  "stemmegiving": {
    "totalGodkjente": 129,
    "fhsGodkjente": 118,
    "totalForkastede": 0,
    "fhsForkastede": 0
  },
  "frammote": {
    "prosent": null,
    "endring": null,
    "prosentStemmegiving": 20.3
  },
  "opptalt": {
    "forelopigFhs": 100,
    "forelopigVts": 100,
    "forelopig": 100,
    "endelig": 100,
    "oppgjor": 0
  },
  "prognose": {
    "beregnet": false,
    "historiskTotalavvik": null
  },
  "partier": [
    {
      "id": {
        "partikategori": 1,
        "partikode": "A",
        "navn": "Arbeiderpartiet"
      },
      "stemmer": {
        "resultat": {
          "prosent": 33.45271,
          "endring": {
            "samme": null,
            "ekvivalent": null
          },
          "antall": {
            "total": 7940,
            "fhs": 7925
          }
        }
      }
    },
    {
      "id": {
        "partikategori": 1,
        "partikode": "SV",
        "navn": "SV - Sosialistisk Venstreparti"
      },
      "stemmer": {
        "resultat": {
          "prosent": 7.76069,
          "endring": {
            "samme": null,
            "ekvivalent": null
          },
          "antall": {
            "total": 1842,
            "fhs": 1839
          }
        }
      }
    },
    {
      "id": {
        "partikategori": 1,
        "partikode": "RØDT",
        "navn": "Rødt"
      },
      "stemmer": {
        "resultat": {
          "prosent": 5.92374,
          "endring": {
            "samme": null,
            "ekvivalent": null
          },
          "antall": {
            "total": 1406,
            "fhs": 1403
          }
        }
      }
    },
    {
      "id": {
        "partikategori": 1,
        "partikode": "SP",
        "navn": "Senterpartiet"
      },
      "stemmer": {
        "resultat": {
          "prosent": 7.88287,
          "endring": {
            "samme": null,
            "ekvivalent": null
          },
          "antall": {
            "total": 1871,
            "fhs": 1871
          }
        }
      }
    },
    {
      "id": {
        "partikategori": 1,
        "partikode": "KRF",
        "navn": "Kristelig Folkeparti"
      },
      "stemmer": {
        "resultat": {
          "prosent": 2.76385,
          "endring": {
            "samme": null,
            "ekvivalent": null
          },
          "antall": {
            "total": 656,
            "fhs": 654
          }
        }
      }
    },
    {
      "id": {
        "partikategori": 1,
        "partikode": "MDG",
        "navn": "Miljøpartiet De Grønne"
      },
      "stemmer": {
        "resultat": {
          "prosent": 4.42385,
          "endring": {
            "samme": null,
            "ekvivalent": null
          },
          "antall": {
            "total": 1050,
            "fhs": 1048
          }
        }
      }
    },
    {
      "id": {
        "partikategori": 1,
        "partikode": "V",
        "navn": "Venstre"
      },
      "stemmer": {
        "resultat": {
          "prosent": 3.07141,
          "endring": {
            "samme": null,
            "ekvivalent": null
          },
          "antall": {
            "total": 729,
            "fhs": 728
          }
        }
      }
    },
    {
      "id": {
        "partikategori": 1,
        "partikode": "H",
        "navn": "Høyre"
      },
      "stemmer": {
        "resultat": {
          "prosent": 18.77818,
          "endring": {
            "samme": null,
            "ekvivalent": null
          },
          "antall": {
            "total": 4457,
            "fhs": 4457
          }
        }
      }
    },
    {
      "id": {
        "partikategori": 1,
        "partikode": "FRP",
        "navn": "Fremskrittspartiet"
      },
      "stemmer": {
        "resultat": {
          "prosent": 11.58205,
          "endring": {
            "samme": null,
            "ekvivalent": null
          },
          "antall": {
            "total": 2749,
            "fhs": 2746
          }
        }
      }
    },
    {
      "id": {
        "partikategori": 2,
        "partikode": "AAN",
        "navn": "Alliansen - Alternativ for Norge"
      },
      "stemmer": {
        "resultat": {
          "prosent": 0.09269,
          "endring": {
            "samme": null,
            "ekvivalent": null
          },
          "antall": {
            "total": 22,
            "fhs": 22
          }
        }
      }
    },
    {
      "id": {
        "partikategori": 2,
        "partikode": "DEMN",
        "navn": "Demokratene"
      },
      "stemmer": {
        "resultat": {
          "prosent": 1.12913,
          "endring": {
            "samme": null,
            "ekvivalent": null
          },
          "antall": {
            "total": 268,
            "fhs": 268
          }
        }
      }
    },
    {
      "id": {
        "partikategori": 2,
        "partikode": "FNB",
        "navn": "Folkeaksjonen Nei til mer bompenger"
      },
      "stemmer": {
        "resultat": {
          "prosent": 0.22751,
          "endring": {
            "samme": null,
            "ekvivalent": null
          },
          "antall": {
            "total": 54,
            "fhs": 54
          }
        }
      }
    },
    {
      "id": {
        "partikategori": 2,
        "partikode": "HELSE",
        "navn": "Helsepartiet"
      },
      "stemmer": {
        "resultat": {
          "prosent": 0.24858,
          "endring": {
            "samme": null,
            "ekvivalent": null
          },
          "antall": {
            "total": 59,
            "fhs": 59
          }
        }
      }
    },
    {
      "id": {
        "partikategori": 2,
        "partikode": "INP",
        "navn": "Industri- og Næringspartiet"
      },
      "stemmer": {
        "resultat": {
          "prosent": 0.13482,
          "endring": {
            "samme": null,
            "ekvivalent": null
          },
          "antall": {
            "total": 32,
            "fhs": 32
          }
        }
      }
    },
    {
      "id": {
        "partikategori": 2,
        "partikode": "KRISTNE",
        "navn": "Partiet De Kristne"
      },
      "stemmer": {
        "resultat": {
          "prosent": 0.36655,
          "endring": {
            "samme": null,
            "ekvivalent": null
          },
          "antall": {
            "total": 87,
            "fhs": 86
          }
        }
      }
    },
    {
      "id": {
        "partikategori": 2,
        "partikode": "LIBS",
        "navn": "Liberalistene"
      },
      "stemmer": {
        "resultat": {
          "prosent": 0.13061,
          "endring": {
            "samme": null,
            "ekvivalent": null
          },
          "antall": {
            "total": 31,
            "fhs": 31
          }
        }
      }
    },
    {
      "id": {
        "partikategori": 2,
        "partikode": "PIR",
        "navn": "Piratpartiet"
      },
      "stemmer": {
        "resultat": {
          "prosent": 0.11376,
          "endring": {
            "samme": null,
            "ekvivalent": null
          },
          "antall": {
            "total": 27,
            "fhs": 27
          }
        }
      }
    },
    {
      "id": {
        "partikategori": 2,
        "partikode": "PP",
        "navn": "Pensjonistpartiet"
      },
      "stemmer": {
        "resultat": {
          "prosent": 1.76111,
          "endring": {
            "samme": null,
            "ekvivalent": null
          },
          "antall": {
            "total": 418,
            "fhs": 418
          }
        }
      }
    },
    {
      "id": {
        "partikategori": 2,
        "partikode": "PS",
        "navn": "Partiet Sentrum"
      },
      "stemmer": {
        "resultat": {
          "prosent": 0.15589,
          "endring": {
            "samme": null,
            "ekvivalent": null
          },
          "antall": {
            "total": 37,
            "fhs": 37
          }
        }
      }
    },
    {
      "id": {
        "partikategori": 3,
        "partikode": "BLANKE",
        "navn": "Blanke"
      },
      "stemmer": {
        "resultat": {
          "prosent": 0.72046,
          "endring": {
            "samme": null,
            "ekvivalent": null
          },
          "antall": {
            "total": 171,
            "fhs": 170
          }
        }
      }
    },
    {
      "id": {
        "partikategori": 0,
        "partikode": "Andre",
        "navn": "Andre"
      },
      "stemmer": {
        "resultat": {
          "prosent": 4.36065,
          "endring": {
            "samme": null,
            "ekvivalent": null
          },
          "antall": {
            "total": 1035,
            "fhs": 1034
          }
        }
      }
    },
    {
      "id": {
        "partikategori": 0,
        "partikode": "Andre2",
        "navn": "Andre2"
      },
      "stemmer": {
        "resultat": {
          "prosent": 0,
          "endring": {
            "samme": null,
            "ekvivalent": null
          },
          "antall": {
            "total": 0,
            "fhs": 0
          }
        }
      }
    }
  ],
  "_links": {
    "related": [],
    "self": {
      "nr": "0000",
      "href": "/2021/st/01/3004/0000",
      "hrefNavn": "/2021/st/%C3%B8stfold/fredrikstad/uoppgitt+krets",
      "navn": "Uoppgitt krets",
      "forelopigFhs": 100,
      "forelopigVts": 100,
      "forelopig": 100,
      "endelig": 100,
      "oppgjor": 0
    },
    "up": {
      "nr": "3004",
      "href": "/2021/st/01/3004",
      "hrefNavn": "/2021/st/%C3%B8stfold/fredrikstad",
      "navn": "Fredrikstad"
    }
  }
}
